jsms.py
jsms-0.0.4.dist-info/LICENSE
jsms-0.0.4.dist-info/METADATA
jsms-0.0.4.dist-info/WHEEL
jsms-0.0.4.dist-info/top_level.txt
jsms-0.0.4.dist-info/RECORD
