Metadata-Version: 2.1
Name: jsms
Version: 0.0.4
Summary: JSMS's officially supported Python client library
Home-page: https://github.com/jpush/jsms-api-python-client
Author: jpush
Author-email: support@jpush.cn
License: MIT
Keywords: jiguang jsms python-sdk
Platform: UNKNOWN
Requires-Dist: requests
